sw6_api/__init__.py
sw6_api/sw6_api.py
sw6_api-1.0.4.dist-info/LICENSE
sw6_api-1.0.4.dist-info/METADATA
sw6_api-1.0.4.dist-info/WHEEL
sw6_api-1.0.4.dist-info/top_level.txt
sw6_api-1.0.4.dist-info/RECORD
