Metadata-Version: 2.1
Name: sw6-api
Version: 1.0.4
Summary: sw6_api
Author-email: Example Author <author@example.com>
Requires-Python: >=3.9
License-File: LICENSE
